setup.py
yuanlanlab_build/__init__.py
yuanlanlab_build/build.py
yuanlanlab_build.egg-info/PKG-INFO
yuanlanlab_build.egg-info/SOURCES.txt
yuanlanlab_build.egg-info/dependency_links.txt
yuanlanlab_build.egg-info/top_level.txt