Metadata-Version: 2.1
Name: yuanlanlab-build
Version: 0.0.0.10
Summary: 空间链接：https://space.bilibili.com/3546564903569609
Author: 元蓝先生@B站
License: This work is licensed under a Creative Commons Attribution-NonCommercial-NoDerivatives 4.0 International License.
